Metadata-Version: 1.0
Name: schatz
Version: 1.0.8
Summary: Schatz integration package for Python 3
Home-page: UNKNOWN
Author: Egor Litvinenko
Author-email: e.v.litvinenko.1@gmail.com
License: Apache 2.0
Platform: UNKNOWN
